nxdk_pgraph_test_repacker/__about__.py
nxdk_pgraph_test_repacker/__init__.py
nxdk_pgraph_test_repacker/__main__.py
nxdk_pgraph_test_repacker-0.0.4.dist-info/METADATA
nxdk_pgraph_test_repacker-0.0.4.dist-info/WHEEL
nxdk_pgraph_test_repacker-0.0.4.dist-info/entry_points.txt
nxdk_pgraph_test_repacker-0.0.4.dist-info/licenses/LICENSE.txt
nxdk_pgraph_test_repacker-0.0.4.dist-info/RECORD
