Metadata-Version: 2.4
Name: nxdk-pgraph-test-repacker
Version: 0.0.4
Summary: Reconfigures nxdk_pgraph_tester ISOs
Project-URL: Documentation, https://github.com/abaire/nxdk-pgraph-test-repacker#readme
Project-URL: Issues, https://github.com/abaire/nxdk-pgraph-test-repacker/issues
Project-URL: Source, https://github.com/abaire/nxdk-pgraph-test-repacker
Author-email: Erik Abair <erik.abair@bearbrains.work>
License-Expression: MIT
License-File: LICENSE.txt
Keywords: nv2a,pgraph,xbox,xemu
Classifier: Development Status :: 4 - Beta
Classifier: Programming Language :: Python
Classifier: Programming Language :: Python :: 3.9
Classifier: Programming Language :: Python :: 3.10
Classifier: Programming Language :: Python :: 3.11
Classifier: Programming Language :: Python :: 3.12
Classifier: Programming Language :: Python :: Implementation :: CPython
Classifier: Programming Language :: Python :: Implementation :: PyPy
Requires-Python: >=3.9
Requires-Dist: platformdirs~=4.3.6
Requires-Dist: requests~=2.32.3
